ubot/__init__.py
ubot/bot.py
ubot-8.0.0.dist-info/METADATA
ubot-8.0.0.dist-info/WHEEL
ubot-8.0.0.dist-info/top_level.txt
ubot-8.0.0.dist-info/RECORD
